{"cameraMode":{"drawMode":0,"name":"Shaded","section":"Shading Mode"},"sceneLighting":true,"audioPlay":false,"sceneViewState":{"m_AlwaysRefresh":false,"showFog":true,"showSkybox":true,"showFlares":true,"showImageEffects":true,"showParticleSystems":true,"showVisualEffectGraphs":true,"m_FxEnabled":true},"in2DMode":false,"pivot":{"x":0.09100997447967529,"y":0.9591748118400574,"z":-14.291702270507813},"rotation":{"x":-0.3182936906814575,"y":-0.008799517527222634,"z":0.0030207601375877859,"w":-0.9477664232254028},"size":1.6343916654586793,"orthographic":false}